main.py
oip_checksum_validator-0.1.3.dist-info/METADATA
oip_checksum_validator-0.1.3.dist-info/WHEEL
oip_checksum_validator-0.1.3.dist-info/entry_points.txt
oip_checksum_validator-0.1.3.dist-info/top_level.txt
oip_checksum_validator-0.1.3.dist-info/RECORD
