Metadata-Version: 2.4
Name: oip-checksum-validator
Version: 0.1.3
Project-URL: Homepage, https://openinnovation.ai/
Classifier: Programming Language :: Python :: 3.12
Classifier: Operating System :: OS Independent
Classifier: Programming Language :: Python :: Implementation :: CPython
Requires-Python: >=3.12
Requires-Dist: blake3>=1.0.8
